iilog/__c.py
iilog/__init__.py
iilog/__version__.py
iilog/filters.py
iilog/formatters.py
iilog/handlers.py
iilog/loggers.py
iilog_pckg-0.0.4.dist-info/LICENSE
iilog_pckg-0.0.4.dist-info/METADATA
iilog_pckg-0.0.4.dist-info/WHEEL
iilog_pckg-0.0.4.dist-info/top_level.txt
iilog_pckg-0.0.4.dist-info/RECORD
