Metadata-Version: 2.1
Name: iilog-pckg
Version: 0.0.4
Summary: iilog: alternative library to logging
Home-page: https://github.com/kyasuda516/iilog-pckg
Download-URL: https://github.com/kyasuda516/iilog-pckg
Author: Kanta Yasuda
License: MIT license
Keywords: iilog,iilog-pckg,logging,logger,log
Classifier: Intended Audience :: Developers
Classifier: License :: OSI Approved :: MIT License
Classifier: Natural Language :: English
Classifier: Topic :: System :: Logging
Classifier: Programming Language :: Python
Classifier: Programming Language :: Python :: 3
Classifier: Programming Language :: Python :: 3.8
Classifier: Programming Language :: Python :: 3.9
Classifier: Programming Language :: Python :: 3.10
Classifier: Programming Language :: Python :: 3.11
Classifier: Programming Language :: Python :: 3 :: Only
Requires-Python: >=3.8
License-File: LICENSE
Requires-Dist: PyYAML (>=6.0)
